tardataset/__init__.py
tardataset/bsontar.py
tardataset/entries.py
tardataset/tarfile.py
tardataset-0.1.6.dist-info/LICENSE
tardataset-0.1.6.dist-info/METADATA
tardataset-0.1.6.dist-info/WHEEL
tardataset-0.1.6.dist-info/entry_points.txt
tardataset-0.1.6.dist-info/top_level.txt
tardataset-0.1.6.dist-info/zip-safe
tardataset-0.1.6.dist-info/RECORD
