Metadata-Version: 2.1
Name: tardataset
Version: 0.1.6
Summary: A dataset format based on BSON and tar file.
Home-page: https://github.com/XoriieInpottn/tardataset
Author: xi
Author-email: gylv@mail.ustc.edu.cn
License: BSD-3-Clause License
Keywords: dataset,file format
Platform: any
Classifier: Programming Language :: Python :: 3.6
Classifier: Programming Language :: Python :: 3.7
Classifier: Programming Language :: Python :: 3.8
Requires-Dist: numpy
Requires-Dist: pymongo
Requires-Dist: tqdm
